odoo/addons/l10n_th_partner/README.rst
odoo/addons/l10n_th_partner/__init__.py
odoo/addons/l10n_th_partner/__manifest__.py
odoo/addons/l10n_th_partner/hooks.py
odoo/addons/l10n_th_partner/data/res.partner.company.type.csv
odoo/addons/l10n_th_partner/data/res.partner.title.csv
odoo/addons/l10n_th_partner/i18n/en_US.po
odoo/addons/l10n_th_partner/i18n/l10n_th_partner.pot
odoo/addons/l10n_th_partner/i18n/th.po
odoo/addons/l10n_th_partner/i18n/th_TH.po
odoo/addons/l10n_th_partner/models/__init__.py
odoo/addons/l10n_th_partner/models/res_company.py
odoo/addons/l10n_th_partner/models/res_config_settings.py
odoo/addons/l10n_th_partner/models/res_partner.py
odoo/addons/l10n_th_partner/models/res_partner_company_type.py
odoo/addons/l10n_th_partner/readme/CONTRIBUTORS.md
odoo/addons/l10n_th_partner/readme/DESCRIPTION.md
odoo/addons/l10n_th_partner/static/description/icon.png
odoo/addons/l10n_th_partner/static/description/index.html
odoo/addons/l10n_th_partner/tests/__init__.py
odoo/addons/l10n_th_partner/tests/test_l10n_th_partner.py
odoo/addons/l10n_th_partner/views/res_company_view.xml
odoo/addons/l10n_th_partner/views/res_config_settings_views.xml
odoo/addons/l10n_th_partner/views/res_partner_company_type_view.xml
odoo/addons/l10n_th_partner/views/res_partner_view.xml
odoo/addons/l10n_th_partner/views/res_users_view.xml
odoo_addon_l10n_th_partner-18.0.1.1.0.dist-info/METADATA
odoo_addon_l10n_th_partner-18.0.1.1.0.dist-info/WHEEL
odoo_addon_l10n_th_partner-18.0.1.1.0.dist-info/top_level.txt
odoo_addon_l10n_th_partner-18.0.1.1.0.dist-info/RECORD
