Metadata-Version: 2.1
Name: odoo-addon-l10n_th_partner
Version: 18.0.1.1.0
Requires-Python: >=3.10
Requires-Dist: odoo-addon-partner_company_type==18.0.*
Requires-Dist: odoo-addon-partner_firstname==18.0.*
Requires-Dist: odoo==18.0.*
Summary: Thai Localization - Partner
Home-page: https://github.com/OCA/l10n-thailand
License: AGPL-3
Author: Ecosoft, Odoo Community Association (OCA)
Author-email: support@odoo-community.org
Classifier: Programming Language :: Python
Classifier: Framework :: Odoo
Classifier: Framework :: Odoo :: 18.0
Classifier: License :: OSI Approved :: GNU Affero General Public License v3
Classifier: Development Status :: 4 - Beta
